polars_qf-0.1.0.dist-info/METADATA
polars_qf-0.1.0.dist-info/WHEEL
polars_qf-0.1.0.dist-info/licenses/LICENSE
polars_qf.libs/libgcc_s-b5472b99.so.1
polars_qf/_utils.py
polars_qf/_quant_factors.py
polars_qf/__init__.py
polars_qf/_polars_qf_core.cpython-310-i386-linux-gnu.so
polars_qf-0.1.0.dist-info/RECORD
