Metadata-Version: 2.4
Name: polars_qf
Version: 0.1.0
Classifier: Development Status :: 1 - Planning
Classifier: License :: OSI Approved :: Apache Software License
Classifier: Topic :: Scientific/Engineering
Classifier: Programming Language :: Rust
Classifier: Programming Language :: Python :: Implementation :: CPython
Classifier: Programming Language :: Python :: Implementation :: PyPy
Requires-Dist: polars >=1
License-File: LICENSE
Summary: A quant factor plugin for polars
Author: cyber-zhs <cyber-zhs@tuta.io>
Author-email: cyber-zhs <cyber_zhs@sohu.com>
License: Apache-2.0
Requires-Python: >=3.9
Project-URL: Repository, https://github.com/cyber-zhs/polars-qf
Project-URL: Changelog, https://github.com/cyber-zhs/polars-qf/releases
